{
  "name": "ripple-vault-client",
  "version": "0.4.8",
  "homepage": "https://github.com/ripple/ripple-vault-client",
  "description": "The Ripple JavaScript Blobvault Client",
  "main": "./ripple-vault-client.js",
  "dependencies": {},
  "_release": "0.4.8",
  "_resolution": {
    "type": "version",
    "tag": "v0.4.8",
    "commit": "ceca488335614ddd32bcfd6681ee8ea32feb66da"
  },
  "_source": "git://github.com/ripple/bower-ripple-vault-client.git",
  "_target": "~0.4.7",
  "_originalSource": "ripple-vault-client"
}